README.md
setup.py
mb_db/__command_line.py
mb_db/__init__.py
mb_db/example_config.yaml
mb_db/mb_datasource.py
mb_db/mb_db_column.py
mb_db/mb_db_connection.py
mb_db/mb_db_rps_stats.py
mb_db/mb_db_table.py
mb_db/mb_db_table_tracker.py
mb_db/table_utils.py
mockingbird_db.egg-info/PKG-INFO
mockingbird_db.egg-info/SOURCES.txt
mockingbird_db.egg-info/dependency_links.txt
mockingbird_db.egg-info/entry_points.txt
mockingbird_db.egg-info/requires.txt
mockingbird_db.egg-info/top_level.txt