Metadata-Version: 2.1
Name: mockingbird-db
Version: 1.0
Summary: Mockingbird-DB: Populate databases with synthetic data
Home-page: https://github.com/openraven/mockingbird-db
